svgs/__init__.py
svgs/svgs.py
svgs-0.0.1.dist-info/LICENSE.txt
svgs-0.0.1.dist-info/METADATA
svgs-0.0.1.dist-info/WHEEL
svgs-0.0.1.dist-info/top_level.txt
svgs-0.0.1.dist-info/RECORD
