Metadata-Version: 2.1
Name: svgs
Version: 0.0.1
Summary: A library for creating static and animated SVGs
Home-page: https://gitlab.com/davidwoodburn/svg
Author: David Woodburn
Author-email: david.woodburn@icloud.com
Classifier: Programming Language :: Python :: 3
Classifier: License :: OSI Approved :: MIT License
Classifier: Operating System :: OS Independent
Requires-Python: >=3.6
License-File: LICENSE.txt
Requires-Dist: numpy
